Metadata-Version: 1.0
Name: django-smileys
Version: 0.1.1-pre1
Summary: Easily replace things like :) and B-) with smilies on your Django-powered site.
Home-page: http://bitbucket.org/codekoala/django-smileys/
Author: Josh VanderLinden
Author-email: codekoala@gmail.com
License: BSD
Keywords: django,image,smiley,useless,fun
Platform: UNKNOWN
Classifier: Development Status :: 4 - Beta
Classifier: Environment :: Web Environment
Classifier: Framework :: Django
Classifier: Intended Audience :: Developers
Classifier: Intended Audience :: End Users/Desktop
Classifier: License :: OSI Approved :: BSD License
Classifier: Natural Language :: English
Classifier: Operating System :: OS Independent
Classifier: Programming Language :: Python
Classifier: Topic :: Artistic Software
Classifier: Topic :: Internet :: WWW/HTTP :: Dynamic Content
Classifier: Topic :: Multimedia :: Graphics
